{"Action":{"TraceId":"80000082-0008-ff00-b63f-84710c7967bb","HttpMethod":"POST","ControllerName":"WriteOffInventory","ActionName":"AddWriteOffInventory","ActionParameters":{"wvm":{"WriteOffId":0,"InventoryId":2,"WriteOffReasonId":1,"WriteOffQty":1,"Name":"Alexa"}},"RequestUrl":"https://localhost:44358/api/WriteOffInventory/CreateWriteOff","IpAddress":"::1","ResponseStatus":"OK","ResponseStatusCode":200},"EventType":"WriteOffInventory/AddWriteOffInventory","Environment":{"UserName":"User","MachineName":"LAPTOP-G49DL6P0","DomainName":"LAPTOP-G49DL6P0","CallingMethodName":"team40_iteration6_user.Controllers.WriteOffInventoryController.AddWriteOffInventory()","AssemblyName":"team40_iteration6_user, Version=1.0.0.0, Culture=neutral, PublicKeyToken=null","Culture":"en-ZA"},"StartDate":"2023-04-30T23:41:20.1196557Z","EndDate":"2023-04-30T23:41:20.1312664Z","Duration":12}